cryolo_relion_it/CorrectPath.py
cryolo_relion_it/CryoloExternalJob.py
cryolo_relion_it/CryoloFineTuneJob.py
cryolo_relion_it/CryoloPipeline.py
cryolo_relion_it/__init__.py
cryolo_relion_it/cryolo_relion_it.py
cryolo_relion_it/options.py
cryolo_relion_it/relion_it_config.py
relion_yolo_it/CorrectPath.py
relion_yolo_it/CryoloExternalJob.py
relion_yolo_it/CryoloFineTuneJob.py
relion_yolo_it/CryoloPipeline.py
relion_yolo_it/__init__.py
relion_yolo_it/cryolo_relion_it.py
relion_yolo_it/options.py
relion_yolo_it/relion_it_config.py
relion_yolo_it-0.3.0.1.data/scripts/CryoloExternalJob.py
relion_yolo_it-0.3.0.1.data/scripts/CryoloFineTuneJob.py
relion_yolo_it-0.3.0.1.data/scripts/CryoloPipeline.py
relion_yolo_it-0.3.0.1.data/scripts/cryolo_relion_it.py
relion_yolo_it-0.3.0.1.dist-info/LICENSE
relion_yolo_it-0.3.0.1.dist-info/METADATA
relion_yolo_it-0.3.0.1.dist-info/WHEEL
relion_yolo_it-0.3.0.1.dist-info/top_level.txt
relion_yolo_it-0.3.0.1.dist-info/RECORD
