Metadata-Version: 2.1
Name: relion-yolo-it
Version: 0.3.0.1
Summary: Updated relion_it with cryolo wrappers
Home-page: https://github.com/DonovanWebb/CryoloRelion/tree/pypiLive
Author: Donovan Webb
Author-email: donovan.webb@diamond.ac.uk
License: GPLv2
Download-URL: https://github.com/DonovanWebb/CryoloRelion/archive/0.3.0.tar.gz
Platform: UNKNOWN
Classifier: Intended Audience :: Science/Research
Classifier: License :: OSI Approved :: GNU General Public License v2 (GPLv2)
Classifier: Natural Language :: English
Requires-Python: ==3.6.8
Requires-Dist: gemmi (==0.2.8)
Requires-Dist: numpy (==1.14.5)
